fdict/__init__.py
fdict/_version.py
fdict/fdict.py
fdict-0.8.1.dist-info/DESCRIPTION.rst
fdict-0.8.1.dist-info/METADATA
fdict-0.8.1.dist-info/RECORD
fdict-0.8.1.dist-info/WHEEL
fdict-0.8.1.dist-info/metadata.json
fdict-0.8.1.dist-info/top_level.txt
